{
  "data": {
    "table": {},
    "cards": [
      {
        "text": [
          "Просим также внимательно ознакомиться с индексом склада для организации самостоятельной доставки.",
          "Приплаты за мерность и малый вес указаны в конце ценника. Напоминаем, что любой счет от 2,000 рублей требует оплаты, и неоплаченные счета будут дополнительно тарифицированы"
        ]
      },
      {
        "text": [
          "Обратите внимание, что в прайс-листе есть позиции с двумя ценами: предоплата и по факту.",
          "Это относится к товарам, находящимся в производстве и ожидающим поступление в ближайший месяц"
        ]
      }
    ]
  }
}
